<?xml version="1.0" encoding="utf-8"?>
<odoo>
	<data>
		<record model="ir.ui.view" id="view_sale_analysis_wizard_form">
			<field name="name">sale.analysis.wizard.form</field>
			<field name="model">sale.analysis.wizard</field>
			<field name="arch" type="xml">
				<form string="Analisis de Ventas">
					<group>
						<group>
							<field name="company_id"/>
							<field name="fiscal_year_id"/>
							<field name="period_start" domain="[('fiscal_year_id','=',fiscal_year_id)]" required="1"/>
							<field name="period_end" domain="[('fiscal_year_id','=',fiscal_year_id)]" required="1"/>
						</group>
					</group>
					<footer>
						<button string="Mostrar" name="get_report" type="object" class="oe_highlight"/>
						or
						<button string="Cancel" class="oe_link" special="cancel"/>
					</footer>
				</form>
			</field>
		</record>

		<record id="sale_analysis_wizard_action" model="ir.actions.act_window">
			<field name="name">Analisis de Ventas</field>
			<field name="type">ir.actions.act_window</field>
			<field name="res_model">sale.analysis.wizard</field>
			<field name="view_mode">form</field>
			<field name="target">new</field>
		</record>

		<menuitem action="sale_analysis_wizard_action" 
				  id="menu_action_sale_analysis_wizard" 
				  parent="sale.menu_sale_report"
				  sequence="9" 
				  groups="account_base_it.group_account_tables_user"/>
	</data>
</odoo>